mkdocs_torillic/__init__.py
mkdocs_torillic/main.html
mkdocs_torillic/mkdocs_theme.yml
mkdocs_torillic/css/ipa.css
mkdocs_torillic/css/logo.png
mkdocs_torillic/css/spoiler.css
mkdocs_torillic/css/statblock.css
mkdocs_torillic/css/torillic.css
mkdocs_torillic/css/torillic/torillic.css
mkdocs_torillic/css/torillic/assets/attrib.json
mkdocs_torillic/css/torillic/assets/paper-texture.png
mkdocs_torillic/css/torillic/assets/splash.png
mkdocs_torillic/css/torillic/assets/torillic-bg.jpg
mkdocs_torillic/css/torillic/assets/coins/copper.png
mkdocs_torillic/css/torillic/assets/coins/electrum.png
mkdocs_torillic/css/torillic/assets/coins/gold.png
mkdocs_torillic/css/torillic/assets/coins/platinum.png
mkdocs_torillic/css/torillic/assets/coins/silver.png
mkdocs_torillic/css/torillic/assets/fonts/Alegreya/Alegreya-Bold.ttf
mkdocs_torillic/css/torillic/assets/fonts/Alegreya/Alegreya-BoldItalic.ttf
mkdocs_torillic/css/torillic/assets/fonts/Alegreya/Alegreya-Italic.ttf
mkdocs_torillic/css/torillic/assets/fonts/Alegreya/Alegreya-Regular.ttf
mkdocs_torillic/css/torillic/assets/fonts/CrimsonText/CrimsonText-Bold.ttf
mkdocs_torillic/css/torillic/assets/fonts/CrimsonText/CrimsonText-BoldItalic.ttf
mkdocs_torillic/css/torillic/assets/fonts/CrimsonText/CrimsonText-Italic.ttf
mkdocs_torillic/css/torillic/assets/fonts/CrimsonText/CrimsonText-Regular.ttf
mkdocs_torillic/css/torillic/assets/fonts/SourceCodePro/SourceCodePro-Bold.ttf
mkdocs_torillic/css/torillic/assets/fonts/SourceCodePro/SourceCodePro-BoldItalic.ttf
mkdocs_torillic/css/torillic/assets/fonts/SourceCodePro/SourceCodePro-Italic.ttf
mkdocs_torillic/css/torillic/assets/fonts/SourceCodePro/SourceCodePro-Regular.ttf
mkdocs_torillic/partials/backlink.html
mkdocs_torillic/partials/global_contents.html
mkdocs_torillic/partials/local_contents.html
mkdocs_torillic/plugins/__init__.py
mkdocs_torillic/plugins/ipa.py
mkdocs_torillic/plugins/spoiler.py
mkdocs_torillic/plugins/statblock.py
mkdocs_torillic-2.4.2.dist-info/licenses/LICENSE
mkdocs_torillic-2.4.2.dist-info/METADATA
mkdocs_torillic-2.4.2.dist-info/WHEEL
mkdocs_torillic-2.4.2.dist-info/entry_points.txt
mkdocs_torillic-2.4.2.dist-info/top_level.txt
mkdocs_torillic-2.4.2.dist-info/RECORD
