Metadata-Version: 2.4
Name: mkdocs-torillic
Version: 2.4.2
Summary: Implementation of the Torillic theme for mkdocs. Convert your markdown TTRPG notes into beautiful HTML!
Author-email: Todd Parsons <todd.e.parsons@gmail.com>
Project-URL: Homepage, https://TEParsons.github.io/mkdocs-torillic
Project-URL: Download, https://github.com/TEParsons/mkdocs-torillic/releases
License-File: LICENSE
Dynamic: license-file
